[
    {
        "id": "M-152A",
        "description": "unicorn IV seal",
        "graphemes": [
            {
                "id": "P324",
                "features": [
                    0,
                    1,
                    0,
                    0,
                    0,
                    0,
                    1,
                    1
                ]
            },
            {
                "id": "P096",
                "features": [
                    0,
                    1,
                    0,
                    5,
                    3,
                    0
                ]
            },
            {
                "id": "P122",
                "features": [
                    0,
                    1,
                    0,
                    0
                ]
            },
            {
                "id": "P385",
                "features": [
                    0,
                    1,
                    0,
                    1
                ]
            }
        ]
    }
]